rsp_jupyter/__init__.py
rsp_jupyter/description.yaml
rsp_jupyter/index.js
rsp_jupyter/posit-icon-fullcolor.svg
rsp_jupyter/rstudio.png
rsp_jupyter-1.5.0.dist-info/METADATA
rsp_jupyter-1.5.0.dist-info/WHEEL
rsp_jupyter-1.5.0.dist-info/top_level.txt
rsp_jupyter-1.5.0.dist-info/RECORD
