Metadata-Version: 2.1
Name: rsp-jupyter
Version: 1.5.0
Summary: Jupyter Notebook integration with RStudio Workbench
Home-page: https://docs.rstudio.com/ide
Author: RStudio
Author-email: ide@rstudio.com
License: GPL-2.0
Project-URL: Documentation, https://docs.rstudio.com/ide
Requires-Dist: notebook
Requires-Dist: ipython
